Modules/Phylogenetic.py
Modules/Prediction.py
Modules/__init__.py
plasmidperxxx-0.1.data/scripts/plasmidperm
plasmidperxxx-0.1.data/scripts/plasmidpermm
plasmidperxxx-0.1.data/scripts/plasmidpermmm
plasmidperxxx-0.1.data/scripts/plasmidperx
plasmidperxxx-0.1.data/scripts/plasmidperxx
plasmidperxxx-0.1.data/scripts/plasmidperxxx
plasmidperxxx-0.1.dist-info/LICENSE
plasmidperxxx-0.1.dist-info/METADATA
plasmidperxxx-0.1.dist-info/WHEEL
plasmidperxxx-0.1.dist-info/top_level.txt
plasmidperxxx-0.1.dist-info/RECORD
